charisma_sdk/__init__.py
charisma_sdk/api.py
charisma_sdk/playthrough.py
charisma_sdk-0.2.0.dist-info/licenses/LICENSE.md
charisma_sdk-0.2.0.dist-info/METADATA
charisma_sdk-0.2.0.dist-info/WHEEL
charisma_sdk-0.2.0.dist-info/top_level.txt
charisma_sdk-0.2.0.dist-info/RECORD
