Metadata-Version: 2.4
Name: charisma-sdk
Version: 0.2.0
Summary: SDK for Charisma.ai
Home-page: https://github.com/charisma-ai/charisma-sdk-python
Author: To Play For Ltd.
Author-email: hello@charisma.ai
License: MIT
Project-URL: Documentation, https://github.com/charisma-ai/charisma-sdk-python/blob/main/README.md
Platform: any
Classifier: Development Status :: 4 - Beta
Classifier: Programming Language :: Python
License-File: LICENSE.md
Requires-Dist: importlib-metadata; python_version < "3.8"
Requires-Dist: pyee
Requires-Dist: python-socketio[client]<5.0,>=4.0
Requires-Dist: requests
Provides-Extra: testing
Requires-Dist: setuptools; extra == "testing"
Requires-Dist: pytest; extra == "testing"
Requires-Dist: pytest-cov; extra == "testing"
Dynamic: license-file
